gplates_ws_proxy/__init__.py
gplates_ws_proxy/__main__.py
gplates_ws_proxy/_auth.py
gplates_ws_proxy/coastlines.py
gplates_ws_proxy/geometry_utils.py
gplates_ws_proxy/gplates.py
gplates_ws_proxy/paleoearth.py
gplates_ws_proxy/plate_model.py
gplates_ws_proxy/quaternions.py
gplates_ws_proxy/reconstruction.py
gplates_ws_proxy/resample_line.py
gplates_ws_proxy/rotation.py
gplates_ws_proxy/spherical_triangle.py
gplates_ws_proxy/subduction_teeth.py
gplates_ws_proxy/topology.py
gplates_ws_proxy/utils.py
gplates_ws_proxy/examples/make_paleo_coastlines_movie.py
gplates_ws_proxy/examples/paleo-coastlines.ipynb
gplates_ws_proxy/examples/plot_paleo_cities.py
gplates_ws_proxy/examples/plot_paleo_coastlines.py
gplates_ws_proxy/examples/plot_paleo_labels.py
gplates_ws_proxy/examples/plot_subduction_zones.py
gplates_ws_proxy/examples/plot_topological_features.py
gplates_ws_proxy/examples/plot_topological_plate_boundaries.py
gplates_ws_proxy/examples/plot_topological_plate_polygons.py
gplates_ws_proxy/examples/reconstruct_shapely_points.py
gplates_ws_proxy-0.1.2.dist-info/LICENSE
gplates_ws_proxy-0.1.2.dist-info/METADATA
gplates_ws_proxy-0.1.2.dist-info/WHEEL
gplates_ws_proxy-0.1.2.dist-info/entry_points.txt
gplates_ws_proxy-0.1.2.dist-info/top_level.txt
gplates_ws_proxy-0.1.2.dist-info/RECORD
